hqapi_client/__init__.py
hqapi_client/example.py
hqapi_client/screenshot.py
hqapi_client-1.1.1.dist-info/licenses/LICENSE
hqapi_client-1.1.1.dist-info/METADATA
hqapi_client-1.1.1.dist-info/WHEEL
hqapi_client-1.1.1.dist-info/top_level.txt
hqapi_client-1.1.1.dist-info/RECORD
