Metadata-Version: 2.4
Name: hqapi_client
Version: 1.1.1
Summary: Python client for HQAPI.com
Author: HQAPI
Keywords: hqapi,screenshot,screenshots
Requires-Python: >=3.8
License-File: LICENSE
Requires-Dist: requests>=2.30.0
Dynamic: license-file
